codinghou/__init__.py
codinghou/main.py
codinghou-0.6.2.dist-info/METADATA
codinghou-0.6.2.dist-info/WHEEL
codinghou-0.6.2.dist-info/top_level.txt
codinghou-0.6.2.dist-info/RECORD
