Metadata-Version: 2.1
Name: codinghou
Version: 0.6.2
Summary: CodingHou package.
Home-page: https://github.com/Douglee/codinghou
Author: douglee
License: UNKNOWN
Platform: UNKNOWN
Classifier: Programming Language :: Python :: 3
Classifier: License :: OSI Approved :: MIT License
Classifier: Operating System :: OS Independent
Requires-Python: >=3.6
Requires-Dist: pyfiglet (>=0.8.post1)
